mp_image_tool_esp32/__init__.py
mp_image_tool_esp32/_version.py
mp_image_tool_esp32/argparse_typed.py
mp_image_tool_esp32/argtypes.py
mp_image_tool_esp32/data_table.py
mp_image_tool_esp32/esptool_io.py
mp_image_tool_esp32/firmware.py
mp_image_tool_esp32/firmware_fileio.py
mp_image_tool_esp32/image_header.py
mp_image_tool_esp32/layouts.py
mp_image_tool_esp32/lfs.py
mp_image_tool_esp32/logger.py
mp_image_tool_esp32/main.py
mp_image_tool_esp32/ota_update.py
mp_image_tool_esp32/partition_table.py
mp_image_tool_esp32/progress_bar.py
mp_image_tool_esp32-0.1.1.dist-info/METADATA
mp_image_tool_esp32-0.1.1.dist-info/WHEEL
mp_image_tool_esp32-0.1.1.dist-info/entry_points.txt
mp_image_tool_esp32-0.1.1.dist-info/licenses/LICENSE
mp_image_tool_esp32-0.1.1.dist-info/RECORD
