Metadata-Version: 2.4
Name: mp-image-tool-esp32
Version: 0.1.1
Summary: Tool for manipulating micropython ESP32 firmware files
Project-URL: Homepage, https://github.com/glenn20/mp-image-tool-esp32
Author-email: glenn20 <6965319+glenn20@users.noreply.github.com>
License: MIT
License-File: LICENSE
Classifier: License :: OSI Approved :: MIT License
Classifier: Operating System :: OS Independent
Classifier: Programming Language :: Python :: 3
Classifier: Programming Language :: Python :: 3.9
Classifier: Programming Language :: Python :: 3.10
Classifier: Programming Language :: Python :: 3.11
Classifier: Programming Language :: Python :: 3.12
Classifier: Programming Language :: Python :: 3.13
Classifier: Topic :: Software Development :: Embedded Systems
Classifier: Topic :: Software Development :: Libraries
Classifier: Typing :: Typed
Requires-Python: >=3.9
Requires-Dist: esptool>=4.6.2
Requires-Dist: more-itertools>=8.8.0
Requires-Dist: rich>=10.12.0
Requires-Dist: typing-extensions>=4.12
Provides-Extra: littlefs
Requires-Dist: littlefs-python>=0.12.0; extra == 'littlefs'
